conference_template_functions.py
lektor_conference_template_functions-0.1.6.dist-info/METADATA
lektor_conference_template_functions-0.1.6.dist-info/WHEEL
lektor_conference_template_functions-0.1.6.dist-info/entry_points.txt
lektor_conference_template_functions-0.1.6.dist-info/top_level.txt
lektor_conference_template_functions-0.1.6.dist-info/RECORD
