Metadata-Version: 2.4
Name: lektor-conference-template-functions
Version: 0.1.6
Summary: Minor functions added to templates for jinja2.
Home-page: https://atrdsymposium.org/
Author: Nelson Brown
Author-email: nelson.brown@faa.gov
License: public domain
Dynamic: author
Dynamic: author-email
Dynamic: home-page
Dynamic: license
Dynamic: summary
